{
	"apiVersion": "extensions/v1beta1",
	"kind": "Deployment",
	"metadata": {
		"annotations": {
			"fabric8.io/iconUrl": "img/icons/spring-boot.svg",
			"fabric8.io/metrics-path": "dashboard/file/kubernetes-pods.json/?var-project=spring-boot-docker-poc&var-version=0.0.1-SNAPSHOT",
			"fabric8.io/scm-tag": "HEAD",
			"fabric8.io/scm-url": "https://github.com/spring-projects/spring-boot/spring-boot-starter-parent/spring-boot-docker-poc"
		},
		"creationTimestamp": "2019-01-27T05:25:10Z",
		"generation": 2,
		"labels": {
			"app": "spring-boot-docker-poc",
			"group": "com.sushilsingh27",
			"provider": "fabric8",
			"version": "0.0.1-SNAPSHOT"
		},
		"name": "spring-boot-docker-poc",
		"namespace": "default",
		"resourceVersion": "49262",
		"selfLink": "/apis/extensions/v1beta1/namespaces/default/deployments/spring-boot-docker-poc",
		"uid": "ea89795f-21f3-11e9-a758-080027beee6e"
	},
	"spec": {
		"progressDeadlineSeconds": 2147483647,
		"replicas": 1,
		"revisionHistoryLimit": 2,
		"selector": {
			"matchLabels": {
				"app": "spring-boot-docker-poc",
				"group": "com.sushilsingh27",
				"provider": "fabric8"
			}
		},
		"strategy": {
			"rollingUpdate": {
				"maxSurge": 1,
				"maxUnavailable": 1
			},
			"type": "RollingUpdate"
		},
		"template": {
			"metadata": {
				"annotations": {
					"fabric8.io/iconUrl": "img/icons/spring-boot.svg",
					"fabric8.io/metrics-path": "dashboard/file/kubernetes-pods.json/?var-project=spring-boot-docker-poc&var-version=0.0.1-SNAPSHOT",
					"fabric8.io/scm-tag": "HEAD",
					"fabric8.io/scm-url": "https://github.com/spring-projects/spring-boot/spring-boot-starter-parent/spring-boot-docker-poc"
				},
				"labels": {
					"app": "spring-boot-docker-poc",
					"group": "com.sushilsingh27",
					"provider": "fabric8",
					"version": "0.0.1-SNAPSHOT"
				}
			},
			"spec": {
				"containers": [
					{
						"env": [
							{
								"name": "KUBERNETES_NAMESPACE",
								"valueFrom": {
									"fieldRef": {
										"apiVersion": "v1",
										"fieldPath": "metadata.namespace"
									}
								}
							}
						],
						"image": "sushilsingh27/spring-boot-docker-poc:snapshot-190127-105430-0516",
						"imagePullPolicy": "IfNotPresent",
						"name": "spring-boot",
						"ports": [
							{
								"containerPort": 8080,
								"name": "http",
								"protocol": "TCP"
							},
							{
								"containerPort": 9779,
								"name": "prometheus",
								"protocol": "TCP"
							},
							{
								"containerPort": 8778,
								"name": "jolokia",
								"protocol": "TCP"
							}
						],
						"resources": {
							
						},
						"securityContext": {
							"privileged": false,
							"procMount": "Default"
						},
						"terminationMessagePath": "/dev/termination-log",
						"terminationMessagePolicy": "File"
					}
				],
				"dnsPolicy": "ClusterFirst",
				"restartPolicy": "Always",
				"schedulerName": "default-scheduler",
				"securityContext": {
					
				},
				"terminationGracePeriodSeconds": 30
			}
		}
	},
	"status": {
		"availableReplicas": 1,
		"conditions": [
			{
				"lastTransitionTime": "2019-01-27T05:25:10Z",
				"lastUpdateTime": "2019-01-27T05:25:10Z",
				"message": "Deployment has minimum availability.",
				"reason": "MinimumReplicasAvailable",
				"status": "True",
				"type": "Available"
			}
		],
		"observedGeneration": 1,
		"readyReplicas": 1,
		"replicas": 2,
		"updatedReplicas": 2
	}
}